{
  "id": 36,
  "biography": [
    {
      "stage": 1,
      "year": "1533年",
      "title": "誕生",
      "description": "小早川隆景（こばやかわたかかげ）は1533年、安芸国（あきのくに）で生まれました。中国地方の大大名・毛利元就（もうりもとなり）の三男です。"
    },
    {
      "stage": 2,
      "year": "1544年",
      "title": "小早川家の養子に",
      "description": "隆景は小早川家の養子となりました。父・元就は息子たちを各地の名家に養子に出し、毛利家の勢力を広げました。"
    },
    {
      "stage": 3,
      "year": "1550年代",
      "title": "水軍の大将",
      "description": "隆景は瀬戸内海（せとないかい）の水軍（すいぐん）を率いるようになりました。海の戦いに優れ、毛利家の海上支配を支えました。"
    },
    {
      "stage": 4,
      "year": "1555年",
      "title": "厳島の戦い",
      "description": "厳島（いつくしま）の戦いでは水軍を率いて活躍しました。父・元就がこの戦いで陶晴賢（すえはるかた）を破り、毛利家は西国の覇者（はしゃ）となりました。"
    },
    {
      "stage": 5,
      "year": "1560年代〜1570年代",
      "title": "毛利家を支える",
      "description": "父・元就が亡くなった後、隆景は兄の吉川元春（きっかわもとはる）と共に甥の毛利輝元（もうりてるもと）を支えました。「毛利両川（もうりりょうせん）」と呼ばれました。"
    },
    {
      "stage": 6,
      "year": "1582年",
      "title": "秀吉との和睦",
      "description": "羽柴秀吉（はしばひでよし）との戦いの最中、本能寺（ほんのうじ）の変が起きました。隆景は秀吉との和睦（わぼく）を進め、毛利家を守りました。"
    },
    {
      "stage": 7,
      "year": "1585年",
      "title": "秀吉に仕える",
      "description": "毛利家は秀吉に臣従（しんじゅう）し、隆景も秀吉の家臣となりました。伊予国（いよのくに）35万石を与えられ、秀吉からも重用されました。"
    },
    {
      "stage": 8,
      "year": "1592年〜",
      "title": "朝鮮出兵",
      "description": "秀吉の朝鮮出兵（ちょうせんしゅっぺい）に参加しました。隆景は水軍を率いて活躍しましたが、戦いの困難さも経験しました。"
    },
    {
      "stage": 9,
      "year": "1595年",
      "title": "秀秋を養子に",
      "description": "秀吉の甥・小早川秀秋（こばやかわひであき）を養子に迎えました。これにより小早川家と豊臣家の結びつきが強まりました。"
    },
    {
      "stage": 10,
      "year": "1597年",
      "title": "隆景の死",
      "description": "小早川隆景は1597年に亡くなりました。65歳でした。知略に優れ、毛利家を支え続けた名将として知られています。"
    }
  ],
  "quiz": [
    {
      "question": "小早川隆景の父は誰でしょうか？",
      "options": ["毛利元就", "毛利輝元", "吉川元春"],
      "correctAnswer": 0,
      "explanation": "小早川隆景（こばやかわたかかげ）の父は毛利元就（もうりもとなり）です。"
    },
    {
      "question": "隆景が率いた軍は何でしょうか？",
      "options": ["水軍", "騎馬隊", "鉄砲隊"],
      "correctAnswer": 0,
      "explanation": "隆景は瀬戸内海の水軍（すいぐん）を率いていました。"
    },
    {
      "question": "隆景と吉川元春は何と呼ばれましたか？",
      "options": ["毛利両川", "両兵衛", "賤ヶ岳の七本槍"],
      "correctAnswer": 0,
      "explanation": "隆景と吉川元春は「毛利両川（もうりりょうせん）」と呼ばれました。"
    },
    {
      "question": "隆景が養子に迎えた人物は誰でしょうか？",
      "options": ["小早川秀秋", "毛利輝元", "豊臣秀頼"],
      "correctAnswer": 0,
      "explanation": "隆景は秀吉の甥・小早川秀秋（こばやかわひであき）を養子に迎えました。"
    },
    {
      "question": "隆景が活躍した戦いはどれでしょうか？",
      "options": ["厳島の戦い", "関ヶ原の戦い", "桶狭間の戦い"],
      "correctAnswer": 0,
      "explanation": "隆景は厳島（いつくしま）の戦いで水軍を率いて活躍しました。"
    }
  ]
}

